srt_time_tweaker/__init__.py
srt_time_tweaker/__main__.py
srt_time_tweaker/get_timings.py
srt_time_tweaker/srt_time_tweaker.py
srt_time_tweaker/valid_timings_line.py
srt_time_tweaker-1.1.0.dist-info/licenses/LICENSE
srt_time_tweaker-1.1.0.dist-info/METADATA
srt_time_tweaker-1.1.0.dist-info/WHEEL
srt_time_tweaker-1.1.0.dist-info/entry_points.txt
srt_time_tweaker-1.1.0.dist-info/top_level.txt
srt_time_tweaker-1.1.0.dist-info/RECORD
