Metadata-Version: 2.4
Name: srt-time-tweaker
Version: 1.1.0
Summary: A no-frills solution for fixing subtitle synchronization issues in SRT (SubRip Subtitle) files by precisely shifting all subtitle timestamps forward or backward using configurable time delays.
Author: भाग्य ज्योति (Bhagya Jyoti)
License: Apache License Version 2.0
Project-URL: Homepage, https://github.com/BhagyaJyoti22006/srt-time-tweaker
Project-URL: Repository, https://github.com/BhagyaJyoti22006/srt-time-tweaker
Project-URL: Issues, https://github.com/BhagyaJyoti22006/srt-time-tweaker/issues
Keywords: srt,time-tweaker,time-tweak,time-shift,subtitle,video,audio,sync,delay,subtitle-edit,srt-editor,cli
Classifier: Programming Language :: Python :: 3
Classifier: License :: OSI Approved :: Apache Software License
Classifier: Operating System :: OS Independent
Classifier: Topic :: Multimedia :: Video
Classifier: Topic :: Multimedia :: Sound/Audio
Classifier: Topic :: Utilities
Classifier: Development Status :: 5 - Production/Stable
Requires-Python: >=3.7
License-File: LICENSE
Dynamic: license-file
